{
  "m_GameObject": {
    "m_FileID": 0,
    "m_PathID": -7065970731565172303
  },
  "m_Enabled": 1,
  "m_Script": {
    "m_FileID": 1,
    "m_PathID": 7647785617504526080
  },
  "m_Name": "",
  "_animations": [
    {
      "animKey": "Idle",
      "animName": "Idle",
      "loop": 1,
      "speed": 1.0,
      "ignoreMissing": 0
    },
    {
      "animKey": "Attack",
      "animName": "Attack",
      "loop": 0,
      "speed": 1.0,
      "ignoreMissing": 0
    },
    {
      "animKey": "Die",
      "animName": "Die",
      "loop": 0,
      "speed": 1.0,
      "ignoreMissing": 0
    },
    {
      "animKey": "Born",
      "animName": "Start",
      "loop": 0,
      "speed": 1.0,
      "ignoreMissing": 0
    },
    {
      "animKey": "Default",
      "animName": "Default",
      "loop": 0,
      "speed": 1.0,
      "ignoreMissing": 0
    },
    {
      "animKey": "Skill_1",
      "animName": "Skill_1",
      "loop": 0,
      "speed": 1.0,
      "ignoreMissing": 0
    },
    {
      "animKey": "Skill_2",
      "animName": "Skill_2",
      "loop": 0,
      "speed": 1.0,
      "ignoreMissing": 0
    },
    {
      "animKey": "Skill_3",
      "animName": "Skill_3",
      "loop": 0,
      "speed": 1.0,
      "ignoreMissing": 0
    },
    {
      "animKey": "Attack_Down",
      "animName": "Attack_Down",
      "loop": 0,
      "speed": 1.0,
      "ignoreMissing": 0
    },
    {
      "animKey": "Stun",
      "animName": "Stun",
      "loop": 0,
      "speed": 1.0,
      "ignoreMissing": 0
    }
  ],
  "_spineSkins": [],
  "_mixSettings": [],
  "_spineScale": 1.0,
  "_enableShowDamageFlash": 1,
  "_cacheBoundsCenter": 1,
  "_faceSwitcher": {
    "m_FileID": 0,
    "m_PathID": 6722999915100060081
  },
  "_front": {
    "skeleton": {
      "m_FileID": 0,
      "m_PathID": -7412182294043936335
    },
    "muzzlaTransform": {
      "m_FileID": 0,
      "m_PathID": 8417957185084864945
    },
    "hitTransform": {
      "m_FileID": 0,
      "m_PathID": -7796557627645478479
    },
    "headTransform": {
      "m_FileID": 0,
      "m_PathID": -435804534066169423
    },
    "shadowTransform": {
      "m_FileID": 0,
      "m_PathID": 0
    },
    "specialPoint0": {
      "m_FileID": 0,
      "m_PathID": 0
    },
    "specialPoint1": {
      "m_FileID": 0,
      "m_PathID": 0
    },
    "specialPoint2": {
      "m_FileID": 0,
      "m_PathID": 0
    },
    "specialPoint3": {
      "m_FileID": 0,
      "m_PathID": 0
    },
    "specialPoint4": {
      "m_FileID": 0,
      "m_PathID": 0
    },
    "specialPoint5": {
      "m_FileID": 0,
      "m_PathID": 0
    },
    "specialPoint6": {
      "m_FileID": 0,
      "m_PathID": 0
    },
    "specialPoint7": {
      "m_FileID": 0,
      "m_PathID": 0
    },
    "specialPoint8": {
      "m_FileID": 0,
      "m_PathID": 0
    },
    "specialPoint9": {
      "m_FileID": 0,
      "m_PathID": 0
    },
    "specialPoint10": {
      "m_FileID": 0,
      "m_PathID": 0
    },
    "specialPoint11": {
      "m_FileID": 0,
      "m_PathID": 0
    },
    "specialPoint12": {
      "m_FileID": 0,
      "m_PathID": 0
    },
    "specialPoint13": {
      "m_FileID": 0,
      "m_PathID": 0
    },
    "specialPoint14": {
      "m_FileID": 0,
      "m_PathID": 0
    },
    "specialPoint15": {
      "m_FileID": 0,
      "m_PathID": 0
    }
  },
  "_back": {
    "skeleton": {
      "m_FileID": 0,
      "m_PathID": 4962592758109583793
    },
    "muzzlaTransform": {
      "m_FileID": 0,
      "m_PathID": -2578967712012420687
    },
    "hitTransform": {
      "m_FileID": 0,
      "m_PathID": -8161091775667619407
    },
    "headTransform": {
      "m_FileID": 0,
      "m_PathID": -435804534066169423
    },
    "shadowTransform": {
      "m_FileID": 0,
      "m_PathID": 0
    },
    "specialPoint0": {
      "m_FileID": 0,
      "m_PathID": 0
    },
    "specialPoint1": {
      "m_FileID": 0,
      "m_PathID": 0
    },
    "specialPoint2": {
      "m_FileID": 0,
      "m_PathID": 0
    },
    "specialPoint3": {
      "m_FileID": 0,
      "m_PathID": 0
    },
    "specialPoint4": {
      "m_FileID": 0,
      "m_PathID": 0
    },
    "specialPoint5": {
      "m_FileID": 0,
      "m_PathID": 0
    },
    "specialPoint6": {
      "m_FileID": 0,
      "m_PathID": 0
    },
    "specialPoint7": {
      "m_FileID": 0,
      "m_PathID": 0
    },
    "specialPoint8": {
      "m_FileID": 0,
      "m_PathID": 0
    },
    "specialPoint9": {
      "m_FileID": 0,
      "m_PathID": 0
    },
    "specialPoint10": {
      "m_FileID": 0,
      "m_PathID": 0
    },
    "specialPoint11": {
      "m_FileID": 0,
      "m_PathID": 0
    },
    "specialPoint12": {
      "m_FileID": 0,
      "m_PathID": 0
    },
    "specialPoint13": {
      "m_FileID": 0,
      "m_PathID": 0
    },
    "specialPoint14": {
      "m_FileID": 0,
      "m_PathID": 0
    },
    "specialPoint15": {
      "m_FileID": 0,
      "m_PathID": 0
    }
  },
  "_useNewSpineFormat": 0
}